{
  "profile": [],
  "proofs": {
    "M_message_passing": {
      "vc___new_closure0": { "prover": "alt-ergo@2.6.2", "time": 0.055 },
      "vc___new_closure0'0": { "prover": "alt-ergo@2.6.2", "time": 0.024 },
      "vc___new_closure0'1": { "prover": "alt-ergo@2.6.2", "time": 0.034 },
      "vc___new_closure4": { "prover": "alt-ergo@2.6.2", "time": 0.035 },
      "vc_alloc_Excl_unit": { "prover": "alt-ergo@2.6.2", "time": 0.041 },
      "vc_as_mut_Resource_Excl_unit": {
        "prover": "alt-ergo@2.6.2",
        "time": 0.032
      },
      "vc_borrow_AtomicInvariant_MessagePassingAtomicInv": {
        "prover": "alt-ergo@2.6.2",
        "time": 0.025
      },
      "vc_borrow_mut_SyncView": { "prover": "alt-ergo@2.6.2", "time": 0.02 },
      "vc_borrow_mut_i32": { "prover": "alt-ergo@2.6.2", "time": 0.026 },
      "vc_closure0": { "prover": "alt-ergo@2.6.2", "time": 0.046 },
      "vc_closure0'0": { "prover": "alt-ergo@2.6.2", "time": 0.05 },
      "vc_closure0'1": { "prover": "alt-ergo@2.6.2", "time": 0.026 },
      "vc_closure0'2": { "prover": "alt-ergo@2.6.2", "time": 0.027 },
      "vc_closure0'3": { "prover": "alt-ergo@2.6.2", "time": 0.043 },
      "vc_closure1": { "prover": "alt-ergo@2.6.2", "time": 0.034 },
      "vc_closure4": { "prover": "alt-ergo@2.6.2", "time": 0.034 },
      "vc_deref_Ghost_Box_Perm_PermCell_i32_Global": {
        "prover": "alt-ergo@2.6.2",
        "time": 0.039
      },
      "vc_deref_Ghost_SyncView": {
        "prover": "alt-ergo@2.6.2",
        "time": 0.024
      },
      "vc_deref_Ghost_i32": { "prover": "alt-ergo@2.6.2", "time": 0.026 },
      "vc_deref_Ghost_ref_AtomicInvariant_MessagePassingAtomicInv": {
        "prover": "alt-ergo@2.6.2",
        "time": 0.028
      },
      "vc_deref_mut_Ghost_Box_Perm_PermCell_i32_Global": {
        "prover": "alt-ergo@2.6.2",
        "time": 0.025
      },
      "vc_deref_mut_Ghost_Option_Resource_Excl_unit": {
        "prover": "alt-ergo@2.6.2",
        "time": 0.029
      },
      "vc_deref_mut_Ghost_Resource_Excl_unit": {
        "prover": "alt-ergo@2.6.2",
        "time": 0.056
      },
      "vc_deref_mut_Ghost_Tokens": {
        "prover": "alt-ergo@2.6.2",
        "time": 0.025
      },
      "vc_elim_Readable": { "prover": "alt-ergo@2.6.2", "time": 0.057 },
      "vc_elim_Synchronisation": {
        "prover": "alt-ergo@2.6.2",
        "time": 0.032
      },
      "vc_get_i32": { "prover": "alt-ergo@2.6.2", "time": 0.042 },
      "vc_into_ghost_i32": { "prover": "alt-ergo@2.6.2", "time": 0.046 },
      "vc_into_inner_Box_Perm_AtomicI32_Global": {
        "prover": "alt-ergo@2.6.2",
        "time": 0.031
      },
      "vc_into_inner_Box_Perm_PermCell_i32_Global": {
        "prover": "alt-ergo@2.6.2",
        "time": 0.028
      },
      "vc_into_inner_Box_Perm_PermCell_i32_Global'0": {
        "prover": "alt-ergo@2.6.2",
        "time": 0.018
      },
      "vc_into_inner_Option_Box_Perm_PermCell_i32_Global": {
        "prover": "alt-ergo@2.6.2",
        "time": 0.036
      },
      "vc_into_inner_Resource_Excl_unit": {
        "prover": "alt-ergo@2.6.2",
        "time": 0.025
      },
      "vc_into_inner_Tokens": { "prover": "alt-ergo@2.6.2", "time": 0.043 },
      "vc_into_inner_tup2_SyncView_AtView_Box_Perm_PermCell_i32_Global": {
        "prover": "alt-ergo@2.6.2",
        "time": 0.032
      },
      "vc_join_unwrap_ScopedJoinHandle_unit": {
        "prover": "alt-ergo@2.6.2",
        "time": 0.036
      },
      "vc_load_Option_Box_Perm_PermCell_i32_Global": {
        "prover": "alt-ergo@2.6.2",
        "time": 0.037
      },
      "vc_message_passing": {
        "tactic": "compute_specified",
        "children": [
          {
            "tactic": "split_vc",
            "children": [
              { "prover": "alt-ergo@2.6.2", "time": 0.045 },
              {
                "tactic": "split_vc",
                "children": [
                  { "prover": "alt-ergo@2.6.2", "time": 0.039 },
                  {
                    "tactic": "split_vc",
                    "children": [
                      { "prover": "alt-ergo@2.6.2", "time": 0.069 },
                      { "prover": "z3@4.15.3", "time": 0.098 },
                      {
                        "tactic": "split_vc",
                        "children": [
                          { "prover": "alt-ergo@2.6.2", "time": 0.05 },
                          { "prover": "alt-ergo@2.6.2", "time": 0.033 },
                          {
                            "tactic": "split_vc",
                            "children": [
                              { "prover": "alt-ergo@2.6.2", "time": 0.04 },
                              { "prover": "alt-ergo@2.6.2", "time": 0.055 },
                              {
                                "tactic": "split_vc",
                                "children": [
                                  {
                                    "prover": "alt-ergo@2.6.2",
                                    "time": 0.059
                                  },
                                  {
                                    "tactic": "split_vc",
                                    "children": [
                                      {
                                        "tactic": "split_vc",
                                        "children": [
                                          {
                                            "prover": "alt-ergo@2.6.2",
                                            "time": 0.044
                                          },
                                          {
                                            "prover": "z3@4.15.3",
                                            "time": 0.771
                                          }
                                        ]
                                      },
                                      {
                                        "prover": "alt-ergo@2.6.2",
                                        "time": 0.053
                                      },
                                      { "prover": "z3@4.15.3", "time": 0.12 }
                                    ]
                                  }
                                ]
                              },
                              { "prover": "z3@4.15.3", "time": 0.086 },
                              { "prover": "alt-ergo@2.6.2", "time": 0.069 },
                              { "prover": "z3@4.15.3", "time": 0.165 },
                              { "prover": "z3@4.15.3", "time": 0.177 },
                              { "prover": "z3@4.15.3", "time": 0.127 }
                            ]
                          }
                        ]
                      },
                      { "prover": "alt-ergo@2.6.2", "time": 0.053 },
                      { "prover": "alt-ergo@2.6.2", "time": 0.058 },
                      { "prover": "alt-ergo@2.6.2", "time": 0.059 },
                      { "prover": "alt-ergo@2.6.2", "time": 0.047 },
                      { "prover": "alt-ergo@2.6.2", "time": 0.036 }
                    ]
                  }
                ]
              },
              { "prover": "alt-ergo@2.6.2", "time": 0.037 }
            ]
          }
        ]
      },
      "vc_new": { "prover": "alt-ergo@2.6.2", "time": 0.016 },
      "vc_new'0": { "prover": "alt-ergo@2.6.2", "time": 0.045 },
      "vc_new_Box_Perm_PermCell_i32_Global": {
        "prover": "alt-ergo@2.6.2",
        "time": 0.028
      },
      "vc_new_Box_Perm_PermCell_i32_Global'0": {
        "prover": "alt-ergo@2.6.2",
        "time": 0.05
      },
      "vc_new_FnGhostWrapper_closure0": {
        "prover": "alt-ergo@2.6.2",
        "time": 0.046
      },
      "vc_new_FnGhostWrapper_closure4": {
        "prover": "alt-ergo@2.6.2",
        "time": 0.036
      },
      "vc_new_MessagePassingAtomicInv": {
        "prover": "alt-ergo@2.6.2",
        "time": 0.059
      },
      "vc_new_MessagePassingAtomicInv'0": {
        "prover": "alt-ergo@2.6.2",
        "time": 0.042
      },
      "vc_new_Option_Resource_Excl_unit": {
        "prover": "alt-ergo@2.6.2",
        "time": 0.047
      },
      "vc_new_Resource_Excl_unit": {
        "prover": "alt-ergo@2.6.2",
        "time": 0.035
      },
      "vc_new_i32": { "prover": "alt-ergo@2.6.2", "time": 0.047 },
      "vc_new_ref_Perm_PermCell_i32": {
        "prover": "alt-ergo@2.6.2",
        "time": 0.036
      },
      "vc_new_refmut_Perm_PermCell_i32": {
        "prover": "alt-ergo@2.6.2",
        "time": 0.054
      },
      "vc_open_MessagePassingAtomicInv": {
        "prover": "alt-ergo@2.6.2",
        "time": 0.046
      },
      "vc_open_MessagePassingAtomicInv'0": {
        "prover": "alt-ergo@2.6.2",
        "time": 0.034
      },
      "vc_reborrow": { "prover": "alt-ergo@2.6.2", "time": 0.023 },
      "vc_replace_State": { "prover": "alt-ergo@2.6.2", "time": 0.02 },
      "vc_scope_closure0": { "prover": "alt-ergo@2.6.2", "time": 0.042 },
      "vc_shoot_i32": { "prover": "alt-ergo@2.6.2", "time": 0.06 },
      "vc_shoot_i32'0": { "prover": "alt-ergo@2.6.2", "time": 0.02 },
      "vc_spawn_closure0": { "prover": "alt-ergo@2.6.2", "time": 0.03 },
      "vc_spawn_closure1": { "prover": "alt-ergo@2.6.2", "time": 0.043 },
      "vc_store_unit": { "prover": "alt-ergo@2.6.2", "time": 0.025 },
      "vc_take_Resource_Excl_unit": {
        "prover": "alt-ergo@2.6.2",
        "time": 0.02
      },
      "vc_unwrap_Box_Perm_PermCell_i32_Global": {
        "prover": "alt-ergo@2.6.2",
        "time": 0.032
      },
      "vc_unwrap_Resource_Excl_unit": {
        "prover": "alt-ergo@2.6.2",
        "time": 0.021
      },
      "vc_unwrap_refmut_Resource_Excl_unit": {
        "prover": "alt-ergo@2.6.2",
        "time": 0.029
      },
      "vc_valid_op_lemma_Excl_unit": {
        "prover": "alt-ergo@2.6.2",
        "time": 0.032
      }
    }
  }
}
