{
  "profile": [],
  "proofs": {
    "M_example": {
      "vc_borrow_UnionFind_i32": { "prover": "alt-ergo", "time": 0.032 },
      "vc_borrow_mut_UnionFind_i32": { "prover": "alt-ergo", "time": 0.032 },
      "vc_clone_Element_i32": { "prover": "alt-ergo", "time": 0.038 },
      "vc_equiv_i32": { "prover": "alt-ergo", "time": 0.026 },
      "vc_example": { "prover": "z3", "time": 0.392 },
      "vc_find_i32": { "prover": "alt-ergo", "time": 0.031 },
      "vc_get_i32": { "prover": "alt-ergo", "time": 0.038 },
      "vc_make_i32": { "prover": "alt-ergo", "time": 0.036 },
      "vc_new_i32": { "prover": "alt-ergo", "time": 0.038 },
      "vc_union_i32": { "prover": "alt-ergo", "time": 0.035 }
    },
    "M_example_addrs_eq": {
      "vc_eq_Element_T": { "prover": "alt-ergo", "time": 0.009 },
      "vc_example_addrs_eq_T": { "prover": "alt-ergo", "time": 0.018 }
    },
    "M_implementation__equiv": {
      "vc_deref_mut_Ghost_refmut_UnionFind_T": {
        "prover": "alt-ergo",
        "time": 0.051
      },
      "vc_eq_Element_T": { "prover": "alt-ergo", "time": 0.049 },
      "vc_equiv_T": { "prover": "alt-ergo", "time": 0.168 },
      "vc_find_T": { "prover": "alt-ergo", "time": 0.054 },
      "vc_new_refmut_UnionFind_T": { "prover": "alt-ergo", "time": 0.055 }
    },
    "M_implementation__find": {
      "vc_find_T": { "prover": "alt-ergo", "time": 0.053 },
      "vc_find_inner_T": { "prover": "alt-ergo", "time": 0.047 }
    },
    "M_implementation__find_inner": {
      "vc_borrow_Node_T": { "prover": "alt-ergo", "time": 0.047 },
      "vc_borrow_mut_Node_T": { "prover": "alt-ergo", "time": 0.022 },
      "vc_clone_Element_T": { "prover": "alt-ergo", "time": 0.046 },
      "vc_deref_Ghost_refmut_UnionFind_T": {
        "prover": "alt-ergo",
        "time": 0.046
      },
      "vc_deref_Rc_PermCell_Node_T_Global": {
        "prover": "alt-ergo",
        "time": 0.045
      },
      "vc_deref_mut_Ghost_refmut_UFInner_T": {
        "prover": "alt-ergo",
        "time": 0.018
      },
      "vc_deref_mut_Ghost_refmut_UnionFind_T": {
        "prover": "alt-ergo",
        "time": 0.055
      },
      "vc_elim_Link": { "prover": "alt-ergo", "time": 0.047 },
      "vc_find_inner_T": { "tactic": "compute_specified", "children": [] },
      "vc_find_inner_T'0": {
        "tactic": "compute_specified",
        "children": [
          {
            "tactic": "split_vc",
            "children": [
              { "prover": "z3", "time": 0.036 },
              { "prover": "alt-ergo", "time": 0.073 },
              { "prover": "alt-ergo", "time": 0.058 },
              { "prover": "z3", "time": 0.05 },
              { "prover": "z3", "time": 0.068 },
              { "prover": "alt-ergo", "time": 0.132 },
              { "prover": "alt-ergo", "time": 0.056 },
              { "prover": "z3", "time": 0.018 },
              { "prover": "z3", "time": 0.034 },
              { "prover": "z3", "time": 0.085 },
              { "prover": "z3", "time": 0.117 },
              { "prover": "z3", "time": 0.029 },
              { "prover": "alt-ergo", "time": 0.109 },
              { "prover": "alt-ergo", "time": 0.167 },
              { "prover": "alt-ergo", "time": 0.126 },
              { "prover": "alt-ergo", "time": 0.086 },
              { "prover": "z3", "time": 0.097 },
              { "prover": "cvc5", "time": 0.293 },
              { "prover": "z3", "time": 0.044 },
              { "prover": "z3", "time": 0.287 },
              { "prover": "z3", "time": 0.033 },
              { "prover": "z3", "time": 0.029 },
              { "prover": "alt-ergo", "time": 0.131 },
              { "prover": "z3", "time": 0.017 },
              { "prover": "z3", "time": 0.014 },
              { "prover": "alt-ergo", "time": 0.147 },
              { "prover": "z3", "time": 0.036 },
              { "prover": "alt-ergo", "time": 0.128 },
              { "prover": "z3", "time": 0.017 },
              { "prover": "z3", "time": 0.016 },
              { "prover": "alt-ergo", "time": 0.161 },
              { "prover": "alt-ergo", "time": 0.138 },
              { "prover": "alt-ergo", "time": 0.194 },
              { "prover": "alt-ergo", "time": 0.068 }
            ]
          }
        ]
      },
      "vc_get_ghost_Snapshot_Element_T": {
        "prover": "alt-ergo",
        "time": 0.047
      },
      "vc_get_mut_ghost_Snapshot_Element_T": {
        "prover": "alt-ergo",
        "time": 0.049
      },
      "vc_new_ref_Perm_PermCell_Node_T": {
        "prover": "alt-ergo",
        "time": 0.047
      },
      "vc_new_refmut_Perm_PermCell_Node_T": {
        "prover": "alt-ergo",
        "time": 0.049
      },
      "vc_new_refmut_UFInner_T": { "prover": "alt-ergo", "time": 0.045 },
      "vc_new_refmut_UnionFind_T": { "prover": "alt-ergo", "time": 0.052 },
      "vc_unwrap_ref_Perm_PermCell_Node_T": {
        "prover": "alt-ergo",
        "time": 0.047
      },
      "vc_unwrap_refmut_Perm_PermCell_Node_T": {
        "prover": "alt-ergo",
        "time": 0.049
      }
    },
    "M_implementation__get": {
      "vc_borrow_Node_T": { "prover": "alt-ergo", "time": 0.04 },
      "vc_deref_Ghost_ref_UnionFind_T": {
        "prover": "alt-ergo",
        "time": 0.051
      },
      "vc_deref_Rc_PermCell_Node_T_Global": {
        "prover": "alt-ergo",
        "time": 0.044
      },
      "vc_elim_Root": { "prover": "alt-ergo", "time": 0.04 },
      "vc_get_T": { "prover": "alt-ergo", "time": 0.119 },
      "vc_get_ghost_Snapshot_Element_T": {
        "prover": "alt-ergo",
        "time": 0.019
      },
      "vc_new_ref_Perm_PermCell_Node_T": {
        "prover": "alt-ergo",
        "time": 0.048
      },
      "vc_unwrap_ref_Perm_PermCell_Node_T": {
        "prover": "alt-ergo",
        "time": 0.048
      }
    },
    "M_implementation__impl_Clone_for_Element_T__clone": {
      "vc_clone_Element_T": { "prover": "alt-ergo", "time": 0.052 },
      "vc_clone_Rc_PermCell_Node_T_Global": {
        "prover": "alt-ergo",
        "time": 0.029
      }
    },
    "M_implementation__impl_Clone_for_Element_T__clone__refines": {
      "refines": { "prover": "alt-ergo", "time": 0.045 }
    },
    "M_implementation__impl_PartialEq_for_Element_T__eq": {
      "vc_eq_Element_T": { "prover": "alt-ergo", "time": 0.049 },
      "vc_ptr_eq_PermCell_Node_T": { "prover": "alt-ergo", "time": 0.039 }
    },
    "M_implementation__impl_PartialEq_for_Element_T__eq__refines": {
      "refines": { "prover": "alt-ergo", "time": 0.036 }
    },
    "M_implementation__impl_UnionFind_T__roots_map": {
      "vc_roots_map_T": { "prover": "alt-ergo", "time": 0.057 }
    },
    "M_implementation__link": {
      "vc_borrow_mut_Node_T": { "prover": "alt-ergo", "time": 0.049 },
      "vc_clone_Element_T": { "prover": "alt-ergo", "time": 0.052 },
      "vc_deref_Rc_PermCell_Node_T_Global": {
        "prover": "alt-ergo",
        "time": 0.051
      },
      "vc_deref_mut_Ghost_refmut_FMap_Snapshot_Element_T_Perm_PermCell_Node_T": {
        "prover": "alt-ergo",
        "time": 0.055
      },
      "vc_deref_mut_Ghost_refmut_UFInner_T": {
        "prover": "alt-ergo",
        "time": 0.045
      },
      "vc_deref_mut_Ghost_refmut_UnionFind_T": {
        "prover": "alt-ergo",
        "time": 0.048
      },
      "vc_elim_Root": { "prover": "alt-ergo", "time": 0.057 },
      "vc_eq_Element_T": { "prover": "alt-ergo", "time": 0.03 },
      "vc_eq_PeanoInt": { "prover": "alt-ergo", "time": 0.048 },
      "vc_get_mut_ghost_Snapshot_Element_T": {
        "prover": "alt-ergo",
        "time": 0.053
      },
      "vc_incr": { "prover": "alt-ergo", "time": 0.05 },
      "vc_link_T": {
        "tactic": "compute_specified",
        "children": [
          {
            "tactic": "split_vc",
            "children": [
              { "prover": "alt-ergo", "time": 0.041 },
              { "prover": "alt-ergo", "time": 0.181 },
              { "prover": "alt-ergo", "time": 0.066 },
              { "prover": "alt-ergo", "time": 0.063 },
              { "prover": "alt-ergo", "time": 0.075 },
              { "prover": "alt-ergo", "time": 0.072 },
              { "prover": "alt-ergo", "time": 0.094 },
              { "prover": "z3", "time": 0.098 },
              { "prover": "alt-ergo", "time": 0.191 },
              { "prover": "alt-ergo", "time": 0.156 },
              { "prover": "alt-ergo", "time": 0.097 },
              { "prover": "alt-ergo", "time": 0.053 },
              { "prover": "cvc5", "time": 0.281 },
              { "prover": "z3", "time": 0.032 },
              { "prover": "cvc5", "time": 0.605 },
              { "prover": "alt-ergo", "time": 0.167 },
              { "prover": "alt-ergo", "time": 0.109 },
              { "prover": "alt-ergo", "time": 0.143 },
              { "prover": "alt-ergo", "time": 0.081 },
              { "prover": "alt-ergo", "time": 0.103 },
              { "prover": "z3", "time": 0.144 },
              { "prover": "alt-ergo", "time": 0.086 },
              { "prover": "alt-ergo", "time": 0.079 },
              { "prover": "z3", "time": 0.03 },
              { "prover": "alt-ergo", "time": 0.069 },
              { "prover": "alt-ergo", "time": 0.109 },
              { "prover": "alt-ergo", "time": 0.077 },
              { "prover": "alt-ergo", "time": 0.075 },
              { "prover": "alt-ergo", "time": 0.098 },
              { "prover": "alt-ergo", "time": 0.095 },
              { "prover": "alt-ergo", "time": 0.181 },
              { "prover": "alt-ergo", "time": 0.142 },
              { "prover": "alt-ergo", "time": 0.14 },
              { "prover": "alt-ergo", "time": 0.079 },
              { "prover": "alt-ergo", "time": 0.12 },
              { "prover": "alt-ergo", "time": 0.104 },
              { "prover": "alt-ergo", "time": 0.138 },
              { "prover": "alt-ergo", "time": 0.048 },
              { "prover": "alt-ergo", "time": 0.123 },
              { "prover": "z3", "time": 0.429 },
              { "prover": "z3", "time": 0.455 },
              {
                "tactic": "split_vc",
                "children": [
                  { "prover": "cvc5", "time": 0.281 },
                  { "prover": "cvc5", "time": 0.269 },
                  { "prover": "z3", "time": 0.354 },
                  { "prover": "z3", "time": 0.182 },
                  { "prover": "z3", "time": 0.111 },
                  { "prover": "cvc5", "time": 0.348 },
                  { "prover": "cvc5", "time": 0.579 },
                  { "prover": "cvc5", "time": 0.437 },
                  { "prover": "cvc5", "time": 0.349 },
                  { "prover": "cvc4", "time": 0.639 },
                  { "prover": "z3", "time": 0.15 },
                  { "prover": "alt-ergo", "time": 0.174 },
                  { "prover": "alt-ergo", "time": 0.16 },
                  { "prover": "alt-ergo", "time": 0.168 },
                  { "prover": "z3", "time": 0.102 },
                  { "prover": "z3", "time": 0.078 },
                  { "prover": "alt-ergo", "time": 0.187 },
                  { "prover": "alt-ergo", "time": 0.2 },
                  { "prover": "z3", "time": 0.099 },
                  { "prover": "z3", "time": 0.165 },
                  { "prover": "z3", "time": 0.23 },
                  { "prover": "alt-ergo", "time": 0.183 },
                  { "prover": "alt-ergo", "time": 0.131 },
                  { "prover": "alt-ergo", "time": 0.154 },
                  { "prover": "alt-ergo", "time": 0.128 },
                  { "prover": "alt-ergo", "time": 0.195 },
                  { "prover": "z3", "time": 0.167 },
                  { "prover": "z3", "time": 0.096 },
                  { "prover": "z3", "time": 0.111 },
                  { "prover": "z3", "time": 0.083 },
                  { "prover": "z3", "time": 0.102 },
                  { "prover": "alt-ergo", "time": 0.189 },
                  { "prover": "z3", "time": 0.132 },
                  { "prover": "alt-ergo", "time": 0.153 },
                  { "prover": "alt-ergo", "time": 0.181 },
                  { "prover": "alt-ergo", "time": 0.149 },
                  { "prover": "alt-ergo", "time": 0.129 },
                  { "prover": "z3", "time": 0.096 },
                  { "prover": "alt-ergo", "time": 0.175 },
                  { "prover": "alt-ergo", "time": 0.192 },
                  { "prover": "z3", "time": 0.121 },
                  { "prover": "z3", "time": 0.088 },
                  { "prover": "z3", "time": 0.156 },
                  { "prover": "z3", "time": 0.106 }
                ]
              },
              { "prover": "alt-ergo", "time": 0.178 },
              { "prover": "z3", "time": 0.101 }
            ]
          }
        ]
      },
      "vc_lt_PeanoInt": { "prover": "alt-ergo", "time": 0.052 },
      "vc_new_refmut_Perm_PermCell_Node_T": {
        "prover": "alt-ergo",
        "time": 0.028
      },
      "vc_new_refmut_UFInner_T": { "prover": "alt-ergo", "time": 0.046 },
      "vc_new_tup2_refmut_Perm_PermCell_Node_T_refmut_FMap_Snapshot_Element_T_Perm_PermCell_Node_T": {
        "prover": "alt-ergo",
        "time": 0.035
      },
      "vc_new_unit": { "prover": "alt-ergo", "time": 0.056 },
      "vc_split_mut_ghost_Snapshot_Element_T": {
        "prover": "alt-ergo",
        "time": 0.034
      },
      "vc_split_refmut_Perm_PermCell_Node_T": {
        "prover": "alt-ergo",
        "time": 0.044
      },
      "vc_unwrap_refmut_Perm_PermCell_Node_T": {
        "prover": "alt-ergo",
        "time": 0.053
      }
    },
    "M_implementation__make": {
      "vc_disjoint_lemma_PermCell_Node_T": {
        "prover": "alt-ergo",
        "time": 0.02
      },
      "vc_elim_Some": { "prover": "alt-ergo", "time": 0.021 },
      "vc_get_ghost_Snapshot_Element_T": {
        "prover": "alt-ergo",
        "time": 0.05
      },
      "vc_insert_ghost_Snapshot_Element_T": {
        "prover": "alt-ergo",
        "time": 0.049
      },
      "vc_into_inner_Perm_PermCell_Node_T": {
        "prover": "alt-ergo",
        "time": 0.036
      },
      "vc_into_inner_refmut_UnionFind_T": {
        "prover": "alt-ergo",
        "time": 0.044
      },
      "vc_make_T": {
        "tactic": "compute_specified",
        "children": [
          {
            "tactic": "split_vc",
            "children": [
              { "prover": "alt-ergo", "time": 0.035 },
              { "prover": "z3", "time": 0.052 },
              { "prover": "alt-ergo", "time": 0.061 },
              { "prover": "z3", "time": 0.229 },
              { "prover": "cvc5", "time": 0.908 }
            ]
          }
        ]
      },
      "vc_new": { "prover": "alt-ergo", "time": 0.038 },
      "vc_new_Node_T": { "prover": "alt-ergo", "time": 0.038 },
      "vc_new_PermCell_Node_T": { "prover": "alt-ergo", "time": 0.036 },
      "vc_new_unit": { "prover": "alt-ergo", "time": 0.047 }
    },
    "M_implementation__new": {
      "vc_into_inner_FMap_Snapshot_Element_T_Perm_PermCell_Node_T": {
        "prover": "alt-ergo",
        "time": 0.048
      },
      "vc_new_Snapshot_Element_T": { "prover": "alt-ergo", "time": 0.048 },
      "vc_new_T": { "prover": "alt-ergo", "time": 0.028 },
      "vc_new_UnionFind_T": { "prover": "alt-ergo", "time": 0.038 }
    },
    "M_implementation__union": {
      "vc_deref_mut_Ghost_refmut_UnionFind_T": {
        "prover": "alt-ergo",
        "time": 0.021
      },
      "vc_find_T": { "prover": "alt-ergo", "time": 0.02 },
      "vc_link_T": { "prover": "alt-ergo", "time": 0.011 },
      "vc_new_refmut_UnionFind_T": { "prover": "alt-ergo", "time": 0.05 },
      "vc_union_T": { "prover": "z3", "time": 0.287 }
    }
  }
}
